regbot/__init__.py
regbot/fetch/__init__.py
regbot/fetch/class_utils.py
regbot/fetch/clinical_trials.py
regbot/fetch/drugsfda.py
regbot/fetch/rxclass.py
regbot-0.1.2.dist-info/LICENSE
regbot-0.1.2.dist-info/METADATA
regbot-0.1.2.dist-info/WHEEL
regbot-0.1.2.dist-info/top_level.txt
regbot-0.1.2.dist-info/RECORD
