Metadata-Version: 2.1
Name: regbot
Version: 0.1.2
Summary: Fetch regulatory approval data for drug terms
Author: Wagner Lab
License: MIT License
Project-URL: Homepage, https://github.com/genomicmedlab/regbot
Project-URL: Documentation, https://github.com/genomicmedlab/regbot
Project-URL: Changelog, https://github.com/genomicmedlab/regbot/releases
Project-URL: Source, https://github.com/genomicmedlab/regbot
Project-URL: Bug Tracker, https://github.com/genomicmedlab/regbot/issues
Classifier: Development Status :: 3 - Alpha
Classifier: Intended Audience :: Science/Research
Classifier: Intended Audience :: Developers
Classifier: Topic :: Scientific/Engineering :: Bio-Informatics
Classifier: License :: OSI Approved :: MIT License
Classifier: Programming Language :: Python :: 3
Classifier: Programming Language :: Python :: 3.11
Classifier: Programming Language :: Python :: 3.12
Classifier: Programming Language :: Python :: 3.13
Requires-Python: >=3.11
License-File: LICENSE
Requires-Dist: requests
Provides-Extra: tests
Requires-Dist: pytest; extra == "tests"
Requires-Dist: pytest-cov; extra == "tests"
Requires-Dist: requests-mock; extra == "tests"
Provides-Extra: dev
Requires-Dist: pre-commit>=3.7.1; extra == "dev"
Requires-Dist: ruff==0.5.0; extra == "dev"
